common/__init__.py
common/common.py
trawler_on_lake-1.0.55.dist-info/LICENSE
trawler_on_lake-1.0.55.dist-info/METADATA
trawler_on_lake-1.0.55.dist-info/WHEEL
trawler_on_lake-1.0.55.dist-info/top_level.txt
trawler_on_lake-1.0.55.dist-info/RECORD
