Metadata-Version: 2.1
Name: trawler-on-lake
Version: 1.0.55
Requires-Python: >=3.7
License-File: LICENSE
Requires-Dist: pyspark==3.5.3
Requires-Dist: requests
Requires-Dist: delta-spark==3.1.0
Requires-Dist: google-analytics-data==0.18.12
Requires-Dist: tomli; python_version < "3.11"
